test_creator.py
test_reader.py
fgc_tools/__init__.py
fgc_tools/cvfunctions.py
fgc_tools/featurehandler.py
fgc_tools/fgccreator.py
fgc_tools/fgcdrawer.py
fgc_tools/fgcreader.py
fgc_tools/readresult.py
fgc_tools/css/style.css
fgc_tools/libs/__init__.py
fgc_tools/libs/binarytools.py
fgc_tools/libs/commonconstants.py
fgc_tools/libs/commonfunctions.py
fgc_tools/libs/hamming.py
fgc_tools/libs/parity.py
unused/fgccreator_2.py
unused/fgcreader_old.py
unused/hamming_2.py
fgc_tools-0.0.27.dist-info/METADATA
fgc_tools-0.0.27.dist-info/WHEEL
fgc_tools-0.0.27.dist-info/licenses/LICENSE
fgc_tools-0.0.27.dist-info/RECORD
