Metadata-Version: 2.1
Name: fgc-tools
Version: 0.0.27
Summary: Fancy Galaxy Code creator and reader package.
Project-URL: Homepage, https://github.com/felixmark/fgc
Project-URL: Bug Tracker, https://github.com/felixmark/fgc/issues
Author-email: Felix Mark <felix.mark@hotmail.com>
License:                     GNU GENERAL PUBLIC LICENSE
License-File: LICENSE
Classifier: License :: OSI Approved :: MIT License
Classifier: Operating System :: OS Independent
Classifier: Programming Language :: Python :: 3
Requires-Python: >=3.7
Requires-Dist: bitarray==2.6.0
Requires-Dist: colour==0.1.5
Requires-Dist: matplotlib==3.5.3
Requires-Dist: numpy==1.19.5
Requires-Dist: opencv-python==4.5.1.48
Requires-Dist: scipy==1.9.1
Requires-Dist: svgwrite==1.4.3
